Metadata-Version: 2.1
Name: erudition
Version: 0.0.12
Summary: Educational Tools
Home-page: https://github.com/endremborza/erudition
Author: Endre Márk Borza
License: MIT
Platform: any
Classifier: License :: OSI Approved :: MIT License
Requires-Python: >=3.8
Provides-Extra: dev
Provides-Extra: complete
License-File: LICENSE
